autobyteus/__init__.py
autobyteus/check_requirements.py
autobyteus/agent/__init__.py
autobyteus/agent/agent.py
autobyteus/agent/exceptions.py
autobyteus/agent/llm_request_assembler.py
autobyteus/agent/processor_option.py
autobyteus/agent/sender_type.py
autobyteus/agent/token_budget.py
autobyteus/agent/tool_invocation.py
autobyteus/agent/bootstrap_steps/__init__.py
autobyteus/agent/bootstrap_steps/agent_bootstrapper.py
autobyteus/agent/bootstrap_steps/base_bootstrap_step.py
autobyteus/agent/bootstrap_steps/mcp_server_prewarming_step.py
autobyteus/agent/bootstrap_steps/system_prompt_processing_step.py
autobyteus/agent/bootstrap_steps/workspace_context_initialization_step.py
autobyteus/agent/context/__init__.py
autobyteus/agent/context/agent_config.py
autobyteus/agent/context/agent_context.py
autobyteus/agent/context/agent_context_registry.py
autobyteus/agent/context/agent_runtime_state.py
autobyteus/agent/events/__init__.py
autobyteus/agent/events/agent_events.py
autobyteus/agent/events/agent_input_event_queue_manager.py
autobyteus/agent/events/event_store.py
autobyteus/agent/events/notifiers.py
autobyteus/agent/events/worker_event_dispatcher.py
autobyteus/agent/factory/__init__.py
autobyteus/agent/factory/agent_factory.py
autobyteus/agent/handlers/__init__.py
autobyteus/agent/handlers/approved_tool_invocation_event_handler.py
autobyteus/agent/handlers/base_event_handler.py
autobyteus/agent/handlers/bootstrap_event_handler.py
autobyteus/agent/handlers/event_handler_registry.py
autobyteus/agent/handlers/generic_event_handler.py
autobyteus/agent/handlers/inter_agent_message_event_handler.py
autobyteus/agent/handlers/lifecycle_event_logger.py
autobyteus/agent/handlers/llm_complete_response_received_event_handler.py
autobyteus/agent/handlers/llm_user_message_ready_event_handler.py
autobyteus/agent/handlers/tool_execution_approval_event_handler.py
autobyteus/agent/handlers/tool_invocation_request_event_handler.py
autobyteus/agent/handlers/tool_result_event_handler.py
autobyteus-1.2.3.dist-info/licenses/LICENSE
autobyteus-1.2.3.dist-info/METADATA
autobyteus-1.2.3.dist-info/WHEEL
autobyteus-1.2.3.dist-info/top_level.txt
autobyteus-1.2.3.dist-info/RECORD
