Metadata-Version: 2.4
Name: autobyteus
Version: 1.2.3
Summary: Multi-Agent framework
Author-email: Ryan Zheng <ryan.zheng.work@gmail.com>
License: MIT License with Additional Terms for Commercial Use
Project-URL: Homepage, https://github.com/AutoByteus/autobyteus
Classifier: Development Status :: 3 - Alpha
Classifier: Intended Audience :: Developers
Classifier: License :: OSI Approved :: MIT License
Classifier: Programming Language :: Python :: 3.11
Requires-Python: <3.12,>=3.11
License-File: LICENSE
Requires-Dist: aiohttp
Requires-Dist: anthropic
Requires-Dist: beautifulsoup4
Requires-Dist: boto3
Requires-Dist: botocore
Requires-Dist: certifi==2025.4.26
Requires-Dist: cryptography
Requires-Dist: google-api-python-client
Requires-Dist: google-genai==1.52.0
Requires-Dist: httpx
Requires-Dist: Jinja2
Requires-Dist: mcp[cli]
Requires-Dist: mistral_common
Requires-Dist: mistralai==1.9.9
Requires-Dist: numpy
Requires-Dist: ollama
Requires-Dist: openai
Requires-Dist: requests
Requires-Dist: websockets>=12.0
Requires-Dist: rich
Requires-Dist: textual
Requires-Dist: tiktoken
Requires-Dist: tokenizers
Provides-Extra: dev
Requires-Dist: build; extra == "dev"
Requires-Dist: coverage; extra == "dev"
Requires-Dist: flake8; extra == "dev"
Requires-Dist: numpy; extra == "dev"
Requires-Dist: pre-commit; extra == "dev"
Requires-Dist: black; extra == "dev"
Requires-Dist: isort; extra == "dev"
Requires-Dist: gitpython==3.1.31; extra == "dev"
Requires-Dist: auto-gpt-plugin-template; extra == "dev"
Requires-Dist: mkdocs; extra == "dev"
Requires-Dist: pytest; extra == "dev"
Requires-Dist: asynctest; extra == "dev"
Requires-Dist: pytest-asyncio; extra == "dev"
Requires-Dist: pytest-benchmark; extra == "dev"
Requires-Dist: pytest-cov; extra == "dev"
Requires-Dist: pytest-integration; extra == "dev"
Requires-Dist: pytest-mock; extra == "dev"
Requires-Dist: vcrpy; extra == "dev"
Requires-Dist: pytest-vcr; extra == "dev"
Requires-Dist: load_dotenv; extra == "dev"
Dynamic: license-file
